ads/__init__.py
ads/admin.py
ads/apps.py
ads/conf.py
ads/forms.py
ads/managers.py
ads/mixins.py
ads/models.py
ads/querysets.py
ads/tests.py
ads/urls.py
ads/utils.py
ads/views.py
ads/migrations/0001_initial.py
ads/migrations/0002_adimage.py
ads/migrations/0003_auto_20170207_1034.py
ads/migrations/0004_remove_ad_image.py
ads/migrations/0005_auto_20180726_1345.py
ads/migrations/__init__.py
ads/static/ads/ads.js
ads/templates/ads/tags/render_ads_zone.html
ads/templatetags/__init__.py
ads/templatetags/ads_tags.py
django_ads-1.1.1.dist-info/LICENSE
django_ads-1.1.1.dist-info/METADATA
django_ads-1.1.1.dist-info/WHEEL
django_ads-1.1.1.dist-info/top_level.txt
django_ads-1.1.1.dist-info/RECORD
