Metadata-Version: 2.1
Name: django-ads
Version: 1.1.1
Summary: Ads Management System for Django Framework
Home-page: https://github.com/razisayyed/django-ads
Author: Razi Alsayyed
Author-email: razi.sayed@gmail.com
License: LICENSE
Platform: OS Independent
Classifier: Development Status :: 2 - Pre-Alpha
Classifier: Environment :: Web Environment
Classifier: Framework :: Django
Classifier: Intended Audience :: Developers
Classifier: License :: OSI Approved :: Apache Software License
Classifier: Operating System :: OS Independent
Classifier: Programming Language :: Python
Classifier: Topic :: Internet :: WWW/HTTP :: Dynamic Content
Classifier: Topic :: Software Development
Classifier: Topic :: Software Development :: Libraries :: Application Frameworks
Requires-Dist: Django (>=1.8)
Requires-Dist: django-appconf (>=1.0.2)
Requires-Dist: django-sekizai (>=0.9.0)
Requires-Dist: django-braces (>=1.10.0)
Requires-Dist: django-js-reverse (>=0.8.2)
Requires-Dist: Pillow
